{
  "page": 350,
  "title": "CANTO VIII.: THE ENCHANTED CAR.",
  "content": "Sacred Texts \n Hinduism \n Index \n Previous \n Next \n \n \n \n CANTO VIII.: THE ENCHANTED CAR.\n \n There gleamed the car with wealth untold\n Of precious gems and burnished gold;\n \n \n \n \n \n \n Nor could the Wind-God's son withdraw\n His rapt gaze from the sight he saw,\n By Vis'vakarmá's  1b self proclaimed\n The noblest work his hand had framed.\n Uplifted in the air it glowed\n Bright as the sun's diurnal road.\n The eye might scan the wondrous frame\n And vainly seek one spot to blame,\n So fine was every part and fair\n With gems inlaid with lavish care.\n No precious stones so rich adorn\n The cars wherein the Gods are borne,\n Prize of the all-resistless might\n That sprang from pain and penance rite,  2b\n Obedient to the master's will\n It moved o'er wood and towering hill,\n A glorious marvel well designed\n By Vis'vakarmá's artist mind,\n Adorned with every fair device\n That decks the cars of Paradise.\n Swift moving as the master chose\n It flew through air or sank or rose,  3b\n And in its fleetness left behind\n The fury of the rushing wind:\n Meet mansion for the good and great,\n The holy, wise, and fortunate.\n Throughout the chariot's vast extent\n Were chambers wide and excellent,\n All pure and lovely to the eyes\n As moonlight shed from cloudless skies.\n Fierce goblins, rovers of the night\n Who cleft the clouds with swiftest flight\n In countless hosts that chariot drew,\n With earrings clashing as they flew.\n \n \n \n \n Footnotes\n 400:1  Pushpak from pushpa a flower. The\n car has been mentioned before in Ravan's\n expedition to carry off Sitá, Book III.\n Canto XXXV.\n 400:2  Lakshmi is the wife of Vishnu and the\n Goddess of Beauty and Felicity. She rose,\n like Aphrodite, from the foam of the sea.\n For an account of her birth aud beauty,\n see Book 1. Canto XLV.\n \n \n Next: Canto IX.: The Ladies' Bower.\n \n\n\n\n\nSacred Texts | \nHinduism\n\n\n\n\n\n« Previous: BOOK V: Canto VII.: Ravan's Palace.\n\n\nIndex\n\n\nNext: BOOK V: Canto IX.: The Ladies' Bower. »",
  "source": "sacred-texts.com",
  "sourceUrl": "https://sacred-texts.com/hin/rama/ry350.htm",
  "scrapedAt": "2026-01-03T07:16:43.375Z",
  "wordCount": 323
}