{
  "parva": "Ashramavasika Parva",
  "parvaNum": 15,
  "section": 40,
  "title": "Book 15Chapter 40",
  "content": "Sacred Texts \n Hinduism \n Mahabharata \n Index \n Book 15 Index \n Previous \n Next \n \n \n \n \n Book 15 in English\n \n \n The Mahabharata in Sanskrit\n Book 15Chapter 40\n \n \n   1\n   [वै]\n       ततॊ निशायां पराप्तायां कृतसायाह्निक करियाः\n       वयासम अभ्यगमन सर्वे ये तत्रासन समागताः\n   2\n  धृतराष्ट्रस तु धर्मात्मा पाण्डवैः सहितस तदा\n       शुचिर एकमनाः सार्धम ऋषिभिस तैर उपाविशत\n   3\n  गान्धार्या सह नार्यस तु सहिताः समुपाविशन\n       पौरजानपदश चापि जनः सार्वॊ यथा वयः\n   4\n  ततॊ वयासॊ महातेजाः पुण्यं भागीरथी जलम\n       अवगाह्याजुहावाथ सर्वाँल लॊकान महामुनिः\n   5\n  पाण्डवानां च ये यॊधाः कौरवाणां च सर्वशः\n       राजानश च महाभागा नानादेशनिवासिनः\n   6\n  ततः सुतुमुलः शब्दॊ जनान्तर जनमेजय\n       परादुरासीद यथापूर्वं कुरुपाण्डवसेनयॊः\n   7\n  ततस ते पार्थिवाः सर्वे भीष्मद्रॊणपुरॊगमाः\n       ससैन्याः सलिलात तस्मात समुत्तस्थुः सहस्रशः\n   8\n  विराटद्रुपदौ चॊभौ सपुत्रौ सह सैनिकौ\n       दरौपदेयाश च सौभद्रॊ राक्षसश च घटॊत्कचः\n   9\n  कर्णदुर्यॊधनौ चॊभौ शकुनिश च महारथः\n       दुःशासनादयश चैव धार्तराष्ट्रा महारथाः\n   10\n  जारासंधिर भगदत्तॊ जलसंधश च पार्थिवः\n      भूरिश्रवाः शलः शल्यॊ वृषसेनश च सानुजः\n  11\n  लक्ष्मणॊ राजपुत्रश च धृष्टद्युम्नस्य चात्मजाः\n      शिखण्डिपुत्राः सर्वे च धृष्टकेतुश च सानुजः\n  12\n  अचलॊ वृषकश चैव राक्षसश चाप्य अलायुधः\n      बाह्लीकः सॊमदत्तश च चेकितानश च पार्थिवः\n  13\n  एते चान्ये च बहवॊ बहुत्वाद ये न कीर्तिताः\n      सर्वे भासुरदेहास ते समुत्तस्थुर जलात ततः\n  14\n  यस्य वीरस्य यॊ वेषॊ यॊ धवजॊ यच च वाहनम\n      तेन तेन वयदृश्यन्त समुपेता नराधिपाः\n  15\n  दिव्याम्बर धराः सर्वे सर्वे भराजिष्णु कुण्डलाः\n      निर्वैरा निरहंकारा विगतक्रॊधमन्यवः\n  16\n  गन्धर्वैर उपगीयन्तः सतूयमानाश च बन्दिभिः\n      दिव्यमाल्याम्बरधरा वृताश चाप्सरसां गणैः\n  17\n  धृतराष्ट्रस्य च तदा दिव्यं चक्षुर नराधिप\n      मुनिः सत्यवती पुत्रः परीतः परादात तपॊबलात\n  18\n  दिव्यज्ञानबलॊपेता गान्धारी च यशस्विनी\n      ददर्श पुत्रांस तान सर्वान ये चान्ये ऽपि रणे हताः\n  19\n  तद अद्भुतम अचिन्त्यं च सुमहद रॊमहर्षणम\n      विस्मितः सजनः सर्वॊ ददर्शानिमिषेक्षणः\n  20\n  तद उत्सव मदॊदग्रं हृष्टनारी नराकुलम\n      ददृशे बलम आयान्तं चित्रं पटगतं यथा\n  21\n  धृतराष्ट्रस तु तान सर्व्वान पश्यन दिव्येन चक्षुषा\n      मुमुदे भरतश्रेष्ठ परसादात तस्य वै मुनेः\n \n \n   1\n   [vai]\n       tato niśāyāṃ prāptāyāṃ kṛtasāyāhnika kriyāḥ\n       vyāsam abhyagaman sarve ye tatrāsan samāgatāḥ\n   2\n  dhṛtarāṣṭras tu dharmātmā pāṇḍavaiḥ sahitas tadā\n       śucir ekamanāḥ sārdham ṛṣibhis tair upāviśat\n   3\n  gāndhāryā saha nāryas tu sahitāḥ samupāviśan\n       paurajānapadaś cāpi janaḥ sārvo yathā vayaḥ\n   4\n  tato vyāso mahātejāḥ puṇyaṃ bhāgīrathī jalam\n       avagāhyājuhāvātha sarvāṁl lokān mahāmuniḥ\n   5\n  pāṇḍavānāṃ ca ye yodhāḥ kauravāṇāṃ ca sarvaśaḥ\n       rājānaś ca mahābhāgā nānādeśanivāsinaḥ\n   6\n  tataḥ sutumulaḥ śabdo janāntar janamejaya\n       prādurāsīd yathāpūrvaṃ kurupāṇḍavasenayoḥ\n   7\n  tatas te pārthivāḥ sarve bhīṣmadroṇapurogamāḥ\n       sasainyāḥ salilāt tasmāt samuttasthuḥ sahasraśaḥ\n   8\n  virāṭadrupadau cobhau saputrau saha sainikau\n       draupadeyāś ca saubhadro rākṣasaś ca ghaṭotkacaḥ\n   9\n  karṇaduryodhanau cobhau śakuniś ca mahārathaḥ\n       duḥśāsanādayaś caiva dhārtarāṣṭrā mahārathāḥ\n   10\n  jārāsaṃdhir bhagadatto jalasaṃdhaś ca pārthivaḥ\n      bhūriśravāḥ śalaḥ śalyo vṛṣasenaś ca sānujaḥ\n  11\n  lakṣmaṇo rājaputraś ca dhṛṣṭadyumnasya cātmajāḥ\n      śikhaṇḍiputrāḥ sarve ca dhṛṣṭaketuś ca sānujaḥ\n  12\n  acalo vṛṣakaś caiva rākṣasaś cāpy alāyudhaḥ\n      bāhlīkaḥ somadattaś ca cekitānaś ca pārthivaḥ\n  13\n  ete cānye ca bahavo bahutvād ye na kīrtitāḥ\n      sarve bhāsuradehās te samuttasthur jalāt tataḥ\n  14\n  yasya vīrasya yo veṣo yo dhvajo yac ca vāhanam\n      tena tena vyadṛśyanta samupetā narādhipāḥ\n  15\n  divyāmbara dharāḥ sarve sarve bhrājiṣṇu kuṇḍalāḥ\n      nirvairā nirahaṃkārā vigatakrodhamanyavaḥ\n  16\n  gandharvair upagīyantaḥ stūyamānāś ca bandibhiḥ\n      divyamālyāmbaradharā vṛtāś cāpsarasāṃ gaṇaiḥ\n  17\n  dhṛtarāṣṭrasya ca tadā divyaṃ cakṣur narādhipa\n      muniḥ satyavatī putraḥ prītaḥ prādāt tapobalāt\n  18\n  divyajñānabalopetā gāndhārī ca yaśasvinī\n      dadarśa putrāṃs tān sarvān ye cānye 'pi raṇe hatāḥ\n  19\n  tad adbhutam acintyaṃ ca sumahad romaharṣaṇam\n      vismitaḥ sajanaḥ sarvo dadarśānimiṣekṣaṇaḥ\n  20\n  tad utsava madodagraṃ hṛṣṭanārī narākulam\n      dadṛśe balam āyāntaṃ citraṃ paṭagataṃ yathā\n  21\n  dhṛtarāṣṭras tu tān sarvvān paśyan divyena cakṣuṣā\n      mumude bharataśreṣṭha prasādāt tasya vai muneḥ\n \n \n \n \n \n Next: Chapter 41\n \n\n\n\n\nSacred Texts | \nHinduism\n\n\n\n\n\n« Previous: The Mahabharata in Sanskrit: Book 15: Chapter 39\n\n\nIndex\n\n\nNext: The Mahabharata in Sanskrit: Book 15: Chapter 41 »",
  "source": "sacred-texts.com",
  "sourceUrl": "https://www.sacred-texts.com/hin/mbs/mbs15040.htm",
  "scrapedAt": "2026-01-03T09:09:22.144Z",
  "wordCount": 559
}